neurokin/__init__.py
neurokin/kinematic_data.py
neurokin/locomotion_states.py
neurokin/neural_data.py
neurokin/constants/__init__.py
neurokin/constants/features_extraction.py
neurokin/constants/open_ephys_structure.py
neurokin/utils/__init__.py
neurokin/utils/experiments/__init__.py
neurokin/utils/experiments/neural_correlates.py
neurokin/utils/experiments/neural_correlates_plot.py
neurokin/utils/experiments/neural_states_helper.py
neurokin/utils/experiments/spider_factory.py
neurokin/utils/features_extraction/__init__.py
neurokin/utils/features_extraction/commons.py
neurokin/utils/features_extraction/core.py
neurokin/utils/features_extraction/feature_extraction.py
neurokin/utils/features_extraction/features/__init__.py
neurokin/utils/features_extraction/features/joint_features.py
neurokin/utils/features_extraction/features/marker_features.py
neurokin/utils/features_extraction/features/misc_features.py
neurokin/utils/helper/__init__.py
neurokin/utils/helper/load_config.py
neurokin/utils/kinematics/__init__.py
neurokin/utils/kinematics/event_detection.py
neurokin/utils/kinematics/import_export.py
neurokin/utils/kinematics/kinematics_processing.py
neurokin/utils/neural/__init__.py
neurokin/utils/neural/exporting.py
neurokin/utils/neural/importing.py
neurokin/utils/neural/neural_plot.py
neurokin/utils/neural/processing.py
neurokin-0.3.8.dist-info/licenses/LICENSE
neurokin-0.3.8.dist-info/METADATA
neurokin-0.3.8.dist-info/WHEEL
neurokin-0.3.8.dist-info/top_level.txt
neurokin-0.3.8.dist-info/RECORD
